AuroraSign/__init__.py
AuroraSign/aurora_certvalidator/__init__.py
AuroraSign/aurora_certvalidator/_asyncio_compat.py
AuroraSign/aurora_certvalidator/_state.py
AuroraSign/aurora_certvalidator/_types.py
AuroraSign/aurora_certvalidator/asn1_types.py
AuroraSign/aurora_certvalidator/authority.py
AuroraSign/aurora_certvalidator/context.py
AuroraSign/aurora_certvalidator/errors.py
AuroraSign/aurora_certvalidator/name_trees.py
AuroraSign/aurora_certvalidator/path.py
AuroraSign/aurora_certvalidator/policy_decl.py
AuroraSign/aurora_certvalidator/policy_tree.py
AuroraSign/aurora_certvalidator/registry.py
AuroraSign/aurora_certvalidator/util.py
AuroraSign/aurora_certvalidator/validate.py
AuroraSign/aurora_certvalidator/version.py
AuroraSign/aurora_certvalidator/fetchers/__init__.py
AuroraSign/aurora_certvalidator/fetchers/api.py
AuroraSign/aurora_certvalidator/fetchers/common_utils.py
AuroraSign/aurora_certvalidator/fetchers/requests_fetchers/__init__.py
AuroraSign/aurora_certvalidator/fetchers/requests_fetchers/cert_fetch_client.py
AuroraSign/aurora_certvalidator/fetchers/requests_fetchers/crl_client.py
AuroraSign/aurora_certvalidator/fetchers/requests_fetchers/ocsp_client.py
AuroraSign/aurora_certvalidator/fetchers/requests_fetchers/util.py
AuroraSign/aurora_certvalidator/ltv/__init__.py
AuroraSign/aurora_certvalidator/ltv/poe.py
AuroraSign/aurora_certvalidator/ltv/types.py
AuroraSign/aurora_certvalidator/revinfo/__init__.py
AuroraSign/aurora_certvalidator/revinfo/_err_gather.py
AuroraSign/aurora_certvalidator/revinfo/archival.py
AuroraSign/aurora_certvalidator/revinfo/constants.py
AuroraSign/aurora_certvalidator/revinfo/manager.py
AuroraSign/aurora_certvalidator/revinfo/validate_crl.py
AuroraSign/aurora_certvalidator/revinfo/validate_ocsp.py
AuroraSign/aurora_signature/__init__.py
AuroraSign/aurora_signature/keys.py
AuroraSign/aurora_signature/stamp.py
AuroraSign/aurora_signature/version.py
AuroraSign/aurora_signature/config/__init__.py
AuroraSign-0.0.41.dist-info/METADATA
AuroraSign-0.0.41.dist-info/WHEEL
AuroraSign-0.0.41.dist-info/top_level.txt
AuroraSign-0.0.41.dist-info/RECORD
